brainpy_datasets/__init__.py
brainpy_datasets/chaos.py
brainpy_datasets/cognitive.py
brainpy_datasets/others.py
brainpy_datasets/vision.py
brainpy_datasets/_src/__init__.py
brainpy_datasets/_src/base.py
brainpy_datasets/_src/dataloader.py
brainpy_datasets/_src/chaos/__init__.py
brainpy_datasets/_src/chaos/base.py
brainpy_datasets/_src/chaos/one_dim_systems.py
brainpy_datasets/_src/chaos/three_dim_systems.py
brainpy_datasets/_src/chaos/two_dim_systems.py
brainpy_datasets/_src/cognitive/__init__.py
brainpy_datasets/_src/cognitive/_utils.py
brainpy_datasets/_src/cognitive/base.py
brainpy_datasets/_src/cognitive/decision_making.py
brainpy_datasets/_src/cognitive/others.py
brainpy_datasets/_src/cognitive/reasoning.py
brainpy_datasets/_src/cognitive/working_memory.py
brainpy_datasets/_src/neuromorphic/__init__.py
brainpy_datasets/_src/others/__init__.py
brainpy_datasets/_src/others/boston_housing.py
brainpy_datasets/_src/transforms/__init__.py
brainpy_datasets/_src/transforms/base.py
brainpy_datasets/_src/utils/__init__.py
brainpy_datasets/_src/utils/_data_utils_v1.py
brainpy_datasets/_src/utils/_data_utils_v2.py
brainpy_datasets/_src/utils/io_utils.py
brainpy_datasets/_src/utils/others.py
brainpy_datasets/_src/utils/progress.py
brainpy_datasets/_src/utils/random.py
brainpy_datasets/_src/vision/__init__.py
brainpy_datasets/_src/vision/base.py
brainpy_datasets/_src/vision/cifar.py
brainpy_datasets/_src/vision/mnist.py
brainpy_datasets-0.0.0.7.dist-info/LICENSE
brainpy_datasets-0.0.0.7.dist-info/METADATA
brainpy_datasets-0.0.0.7.dist-info/WHEEL
brainpy_datasets-0.0.0.7.dist-info/top_level.txt
brainpy_datasets-0.0.0.7.dist-info/RECORD
