Metadata-Version: 2.1
Name: brainpy-datasets
Version: 0.0.0.7
Summary: BrainPy Datasets
Home-page: https://github.com/brainpy/brainpy-datasets
Author: BrainPy Team
Author-email: chao.brain@qq.com
License: GPL-3.0 license
Project-URL: Bug Tracker, https://github.com/brainpy/brainpy-datasets/issues
Project-URL: Source Code, https://github.com/brainpy/brainpy-datasets
Keywords: computational neuroscience,brain-inspired computation,brainpy,dataset,brain modeling,brain dynamics modeling,brain dynamics programming
Classifier: Natural Language :: English
Classifier: Operating System :: OS Independent
Classifier: Programming Language :: Python
Classifier: Programming Language :: Python :: 3
Classifier: Programming Language :: Python :: 3.7
Classifier: Programming Language :: Python :: 3.8
Classifier: Programming Language :: Python :: 3.9
Classifier: Programming Language :: Python :: 3.10
Classifier: Intended Audience :: Science/Research
Classifier: License :: OSI Approved :: Apache Software License
Classifier: Topic :: Scientific/Engineering :: Bio-Informatics
Classifier: Topic :: Scientific/Engineering :: Mathematics
Classifier: Topic :: Scientific/Engineering :: Artificial Intelligence
Classifier: Topic :: Software Development :: Libraries
Requires-Python: >=3.7
License-File: LICENSE
Requires-Dist: brainpy (>=2.2.0)
Requires-Dist: requests
